MANIFEST.in
README.md
setup.py
./qmctoolscl/c_funcs/dnb2_digital_shift.c
./qmctoolscl/c_funcs/dnb2_gen_gray.c
./qmctoolscl/c_funcs/dnb2_gen_natural.c
./qmctoolscl/c_funcs/dnb2_gmat_lsb_to_msb.c
./qmctoolscl/c_funcs/dnb2_integer_to_float.c
./qmctoolscl/c_funcs/dnb2_interlace.c
./qmctoolscl/c_funcs/dnb2_linear_matrix_scramble.c
./qmctoolscl/c_funcs/dnb2_undo_interlace.c
./qmctoolscl/c_funcs/fft_bro_1d_radix2.c
./qmctoolscl/c_funcs/fwht_1d_radix2.c
./qmctoolscl/c_funcs/gdn_digital_permutation.c
./qmctoolscl/c_funcs/gdn_digital_shift.c
./qmctoolscl/c_funcs/gdn_gen_natural.c
./qmctoolscl/c_funcs/gdn_gen_natural_same_base.c
./qmctoolscl/c_funcs/gdn_integer_to_float.c
./qmctoolscl/c_funcs/gdn_interlace.c
./qmctoolscl/c_funcs/gdn_linear_matrix_scramble.c
./qmctoolscl/c_funcs/gdn_undo_interlace.c
./qmctoolscl/c_funcs/ifft_bro_1d_radix2.c
./qmctoolscl/c_funcs/lat_gen_gray.c
./qmctoolscl/c_funcs/lat_gen_linear.c
./qmctoolscl/c_funcs/lat_gen_natural.c
./qmctoolscl/c_funcs/lat_shift_mod_1.c
./qmctoolscl/c_funcs/python_compat.c
qmctoolscl/__init__.py
qmctoolscl/c_funcs.py
qmctoolscl/rand_funcs.py
qmctoolscl/util.py
qmctoolscl/wrapped_funcs.py
qmctoolscl.egg-info/PKG-INFO
qmctoolscl.egg-info/SOURCES.txt
qmctoolscl.egg-info/dependency_links.txt
qmctoolscl.egg-info/requires.txt
qmctoolscl.egg-info/top_level.txt
qmctoolscl/c_funcs/dnb2_digital_shift.c
qmctoolscl/c_funcs/dnb2_gen_gray.c
qmctoolscl/c_funcs/dnb2_gen_natural.c
qmctoolscl/c_funcs/dnb2_gmat_lsb_to_msb.c
qmctoolscl/c_funcs/dnb2_integer_to_float.c
qmctoolscl/c_funcs/dnb2_interlace.c
qmctoolscl/c_funcs/dnb2_linear_matrix_scramble.c
qmctoolscl/c_funcs/dnb2_undo_interlace.c
qmctoolscl/c_funcs/fft_bro_1d_radix2.c
qmctoolscl/c_funcs/fwht_1d_radix2.c
qmctoolscl/c_funcs/gdn_digital_permutation.c
qmctoolscl/c_funcs/gdn_digital_shift.c
qmctoolscl/c_funcs/gdn_gen_natural.c
qmctoolscl/c_funcs/gdn_gen_natural_same_base.c
qmctoolscl/c_funcs/gdn_integer_to_float.c
qmctoolscl/c_funcs/gdn_interlace.c
qmctoolscl/c_funcs/gdn_linear_matrix_scramble.c
qmctoolscl/c_funcs/gdn_undo_interlace.c
qmctoolscl/c_funcs/ifft_bro_1d_radix2.c
qmctoolscl/c_funcs/lat_gen_gray.c
qmctoolscl/c_funcs/lat_gen_linear.c
