Metadata-Version: 2.1
Name: qmctoolscl
Version: 1.1.6
Summary: Quasi-Monte Carlo Tools in PyOpenCL and C
Home-page: https://qmcsoftware.github.io/QMCToolsCL/
Author: Aleksei G Sorokin
Author-email: asorokin@hawk.iit.edu
Requires-Python: >=3.5
Requires-Dist: numpy>=1.17.0
